rwslib/__init__.py
rwslib/builders/README.md
rwslib/builders/__init__.py
rwslib/builders/admindata.py
rwslib/builders/clinicaldata.py
rwslib/builders/common.py
rwslib/builders/constants.py
rwslib/builders/core.py
rwslib/builders/metadata.py
rwslib/builders/modm.py
rwslib/builders_example.py
rwslib/example.py
rwslib/extras/__init__.py
rwslib/extras/audit_event/README.md
rwslib/extras/audit_event/__init__.py
rwslib/extras/audit_event/context.py
rwslib/extras/audit_event/main.py
rwslib/extras/audit_event/parser.py
rwslib/extras/local_cv.py
rwslib/extras/rwscmd/README.md
rwslib/extras/rwscmd/__init__.py
rwslib/extras/rwscmd/data_scrambler.py
rwslib/extras/rwscmd/odmutils.py
rwslib/extras/rwscmd/rws_configurable_dataset/rws_sp.sql
rwslib/extras/rwscmd/rws_configurable_dataset/rws_template.sql
rwslib/extras/rwscmd/rwscmd.py
rwslib/rws_requests/__init__.py
rwslib/rws_requests/biostats_gateway.py
rwslib/rws_requests/odm_adapter.py
rwslib/rwsobjects.py
rwslib-1.2.12.dist-info/LICENSE.txt
rwslib-1.2.12.dist-info/METADATA
rwslib-1.2.12.dist-info/WHEEL
rwslib-1.2.12.dist-info/RECORD
