Metadata-Version: 2.1
Name: rwslib
Version: 1.2.12
Summary: Rave Web Services for Python
Home-page: https://github.com/mdsol/rwslib
License: MIT
Author: Ian Sparks
Author-email: isparks@trialgrid.com
Maintainer: Geoff Low
Maintainer-email: geoff.low@3ds.com
Requires-Python: >=3.7.0,<4
Classifier: Development Status :: 5 - Production/Stable
Classifier: Intended Audience :: Developers
Classifier: License :: OSI Approved :: MIT License
Classifier: Natural Language :: English
Classifier: Programming Language :: Python
Classifier: Programming Language :: Python :: 3
Classifier: Programming Language :: Python :: 3.7
Classifier: Programming Language :: Python :: 3.8
Classifier: Programming Language :: Python :: 3.9
Classifier: Programming Language :: Python :: 3.10
Classifier: Programming Language :: Python :: 3.11
Classifier: Programming Language :: Python :: 3.10
Classifier: Programming Language :: Python :: 3.11
Classifier: Programming Language :: Python :: 3.12
Requires-Dist: click
Requires-Dist: faker
Requires-Dist: lxml
Requires-Dist: requests
Requires-Dist: six
Requires-Dist: urllib3
Project-URL: Documentation, https://rwslib.readthedocs.io
Project-URL: Repository, https://github.com/mdsol/rwslib
